cnspy_relative_pose_evaluation/AssociateRelPoses.py
cnspy_relative_pose_evaluation/ROSBag_MeasObjPoses.py
cnspy_relative_pose_evaluation/ROSBag_ModifyRelPoses.py
cnspy_relative_pose_evaluation/ROSBag_Pose2AbsPoses.py
cnspy_relative_pose_evaluation/ROSBag_Poses2RelPoses.py
cnspy_relative_pose_evaluation/ROSBag_TrueRelPoses.py
cnspy_relative_pose_evaluation/RelPoseMeasEvaluation.py
cnspy_relative_pose_evaluation/RelPoseMeasEvaluationTool.py
cnspy_relative_pose_evaluation/RelPose_ROSBag2CSV.py
cnspy_relative_pose_evaluation/__init__.py
test/__init__.py
test/example.py
test/test_ROSBag_TrueRelPoses.py
test/test_RPME_Tool.py
test/test_RelPoseMeasEvaluation.py
cnspy_relative_pose_evaluation-0.1.18.dist-info/LICENSE
cnspy_relative_pose_evaluation-0.1.18.dist-info/METADATA
cnspy_relative_pose_evaluation-0.1.18.dist-info/WHEEL
cnspy_relative_pose_evaluation-0.1.18.dist-info/entry_points.txt
cnspy_relative_pose_evaluation-0.1.18.dist-info/top_level.txt
cnspy_relative_pose_evaluation-0.1.18.dist-info/RECORD
