Metadata-Version: 2.1
Name: cnspy_relative_pose_evaluation
Version: 0.1.18
Summary: Evaluation of uncertain relative pose measurements.
Home-page: https://github.com/aau-cns/cnspy_relative_pose_evaluation/
Author: Roland Jung
Author-email: roland.jung@aau.at
Project-URL: Bug Tracker, https://github.com/aau-cns/cnspy_relative_pose_evaluation/issues
Classifier: Development Status :: 4 - Beta
Classifier: Intended Audience :: Developers
Classifier: Programming Language :: Python :: 3
Classifier: License :: OSI Approved :: GNU General Public License v3 (GPLv3)
Classifier: Operating System :: OS Independent
Requires-Python: >=3.6
License-File: LICENSE
Requires-Dist: numpy
Requires-Dist: pandas
Requires-Dist: spatialmath-python
Requires-Dist: scipy
Requires-Dist: matplotlib
Requires-Dist: joblib
Requires-Dist: configparser
Requires-Dist: cnspy-numpy-utils
Requires-Dist: cnspy-timestamp-association >=0.2.1
Requires-Dist: cnspy-csv2dataframe >=0.2.3
Requires-Dist: cnspy-trajectory >=0.2.11
Requires-Dist: cnspy-trajectory-evaluation >=0.2.7
Requires-Dist: cnspy-ranging-evaluation >=0.2.9
